<annotation>
		<folder>JPEGImages</folder>
		<filename>maksssksksssmaksssksksss3181.jpg</filename>
		<size>
			   <width>800</width>
			   <height>557</height>
			   <depth>3</depth>
		</size>
		<object>
			   <name>mask</name>
			   <pose>Unspecified</pose>
			   <truncated>0</truncated>
			   <difficult>0</difficult>
			   <bndbox>
				     <xmin>28</xmin>
				     <ymin>234</ymin>
				     <xmax>247</xmax>
				     <ymax>503</ymax>
			   </bndbox>
		</object>
		<object>
			   <name>mask</name>
			   <pose>Unspecified</pose>
			   <truncated>0</truncated>
			   <difficult>0</difficult>
			   <bndbox>
				     <xmin>406</xmin>
				     <ymin>227</ymin>
				     <xmax>646</xmax>
				     <ymax>512</ymax>
			   </bndbox>
		</object>
	</annotation>