<annotation>
		<folder>JPEGImages</folder>
		<filename>maksssksksssmaksssksksss1933.jpg</filename>
		<size>
			   <width>1024</width>
			   <height>742</height>
			   <depth>3</depth>
		</size>
		<object>
			   <name>nomask</name>
			   <pose>Unspecified</pose>
			   <truncated>0</truncated>
			   <difficult>0</difficult>
			   <bndbox>
				     <xmin>656</xmin>
				     <ymin>151</ymin>
				     <xmax>756</xmax>
				     <ymax>304</ymax>
			   </bndbox>
		</object>
		<object>
			   <name>nomask</name>
			   <pose>Unspecified</pose>
			   <truncated>0</truncated>
			   <difficult>0</difficult>
			   <bndbox>
				     <xmin>443</xmin>
				     <ymin>120</ymin>
				     <xmax>550</xmax>
				     <ymax>238</ymax>
			   </bndbox>
		</object>
		<object>
			   <name>nomask</name>
			   <pose>Unspecified</pose>
			   <truncated>0</truncated>
			   <difficult>0</difficult>
			   <bndbox>
				     <xmin>245</xmin>
				     <ymin>242</ymin>
				     <xmax>322</xmax>
				     <ymax>341</ymax>
			   </bndbox>
		</object>
	</annotation>